MANIFEST.in
README.md
meta.json
setup.py
en_aesops_advert/__init__.py
en_aesops_advert/meta.json
en_aesops_advert.egg-info/PKG-INFO
en_aesops_advert.egg-info/SOURCES.txt
en_aesops_advert.egg-info/dependency_links.txt
en_aesops_advert.egg-info/entry_points.txt
en_aesops_advert.egg-info/not-zip-safe
en_aesops_advert.egg-info/requires.txt
en_aesops_advert.egg-info/top_level.txt
en_aesops_advert/en_aesops_advert-0.0.0/README.md
en_aesops_advert/en_aesops_advert-0.0.0/config.cfg
en_aesops_advert/en_aesops_advert-0.0.0/meta.json
en_aesops_advert/en_aesops_advert-0.0.0/tokenizer
en_aesops_advert/en_aesops_advert-0.0.0/textcat/cfg
en_aesops_advert/en_aesops_advert-0.0.0/textcat/model
en_aesops_advert/en_aesops_advert-0.0.0/vocab/key2row
en_aesops_advert/en_aesops_advert-0.0.0/vocab/lookups.bin
en_aesops_advert/en_aesops_advert-0.0.0/vocab/strings.json
en_aesops_advert/en_aesops_advert-0.0.0/vocab/vectors
en_aesops_advert/en_aesops_advert-0.0.0/vocab/vectors.cfg